sqlalchemyp/__init__.py
sqlalchemyp-0.0.5.dist-info/METADATA
sqlalchemyp-0.0.5.dist-info/WHEEL
sqlalchemyp-0.0.5.dist-info/top_level.txt
sqlalchemyp-0.0.5.dist-info/RECORD
