Metadata-Version: 2.1
Name: sqlalchemyp
Version: 0.0.5
Summary: SQLAlchemy Print Query
Home-page: https://github.com/evangilo/sqlalchemyp
Author: Evangilo
Author-email: evangilo@gmail.com
License: MIT
Platform: UNKNOWN
Classifier: Intended Audience :: Developers
Classifier: Programming Language :: Python
Classifier: License :: OSI Approved :: MIT License
Classifier: Programming Language :: Python :: 2.7
Classifier: Programming Language :: Python :: 3.6
Classifier: Programming Language :: Python :: 3.7
Requires-Dist: sqlalchemy
Requires-Dist: sqlparse
